<databaseChangeLog xmlns='http://www.liquibase.org/xml/ns/dbchangelog'
                   xmlns:xsi='http://www.w3.org/2001/XMLSchema-instance'
                   xsi:schemaLocation='http://www.liquibase.org/xml/ns/dbchangelog http://www.liquibase.org/xml/ns/dbchangelog/dbchangelog-2.0.xsd'>
    <changeSet id="028" author="Waldemar">

        <dropForeignKeyConstraint baseTableName="sprint_developers" constraintName="fk_sprint"/>
        <dropForeignKeyConstraint baseTableName="sprint_developers" constraintName="fk_sprint_developers"/>
        <dropPrimaryKey tableName="sprint_developers" constraintName="pk_sprint_developers"/>

        <addPrimaryKey columnNames="id"
                       constraintName="pk_sprint_developers"
                       tableName="sprint_developers" />

        <addForeignKeyConstraint baseColumnNames="sprint_id"
                                 baseTableName="sprint_developers"
                                 constraintName="fk_sprint"
                                 onDelete="CASCADE"
                                 onUpdate="CASCADE"
                                 referencedColumnNames="id"
                                 referencedTableName="sprints"/>

        <addForeignKeyConstraint baseColumnNames="jira_user_login"
                                 baseTableName="sprint_developers"
                                 constraintName="fk_sprint_developers"
                                 referencedColumnNames="login"
                                 referencedTableName="jira_users"/>

    </changeSet>
</databaseChangeLog>